pika_client/__init__.py
pika_client/connector.py
pika_client/consumer.py
pika_client/factory.py
pika_client/launcher.py
pika_client/publisher.py
pika_client/route_setup.py
pika_client-0.5.1.dist-info/METADATA
pika_client-0.5.1.dist-info/RECORD
pika_client-0.5.1.dist-info/WHEEL
pika_client-0.5.1.dist-info/top_level.txt
