Metadata-Version: 2.1
Name: pika-client
Version: 0.5.1
Summary: Pika Client
Home-page: https://github.com/BenjiBackslash/pika_client
Author: Hanan Wiener
Author-email: hanan888@gmail.com
License: MIT
Platform: UNKNOWN
Requires-Dist: pika (==0.12.0)
